assemblycoins
