Metadata-Version: 1.0
Name: assemblycoins
Version: 0.1.2
Summary: Digital Tokens on the Bitcoin Blockchain
Home-page: https://coins.assembly.com
Author: Andrew Barisser
Author-email: barisser@gmail.com
License: MIT
Platform: UNKNOWN
